[
 {"e":"min.add","min":[{"mid":"383f70cc-a325-46d0-bfad-d18bd2c07a4f","kid":411,"lif":3,"xf":260,"yf":516,"lit":11,"xt":260,"yt":517,"did":1,"s":0.0,"t":-0.0040034,"usr":{"uid":19494813,"fn":"Vlad Grasula","ph":"GUI/Avatars/avatar_6","pwr":338359397.0,"vl":18,"lcn":{"lid":3,"mlk":0,"cid":1,"lv":27,"lx":260,"ly":516,"ln":"castle gayskull","kid":411,"sid":5},"aln":{"aid":270704,"an":"Suntlandir Knights","ag":"8;9;7;0","at":"S_u_N","al":"en","cty":{"kid":404,"x":206,"y":543,"l":2,"r":6,"g":false}},"phn":{"kid":404,"x":206,"y":538,"ct":6,"tid":11858},"fid":1,"abp":{"kid1":404,"aid1":270704,"kid2":167,"aid2":95978}},"tid":9,"now":"2017-12-31T21:08:28.1170127Z","upd":"2017-12-31T21:08:28.1130093Z","mt":0.0,"efid":1,"mmb":[]}]}
]
